textco/__init__.py
textco/textco.py
textco-0.0.8.dist-info/LICENSE.txt
textco-0.0.8.dist-info/METADATA
textco-0.0.8.dist-info/WHEEL
textco-0.0.8.dist-info/top_level.txt
textco-0.0.8.dist-info/RECORD
