Metadata-Version: 2.1
Name: textco
Version: 0.0.8
Summary: TEXT analytsis COpilot
Home-page: UNKNOWN
Author: Dr Anna Sung and Prof Kelvin Leong
Author-email: <k.leong@chester.ac.uk>
License: UNKNOWN
Keywords: python,first package
Platform: UNKNOWN
Classifier: Development Status :: 3 - Alpha
Classifier: Intended Audience :: Science/Research
Classifier: Intended Audience :: Education
Classifier: Intended Audience :: Other Audience
Classifier: Programming Language :: Python :: 2
Classifier: Programming Language :: Python :: 3
Classifier: Operating System :: MacOS :: MacOS X
Classifier: Operating System :: Microsoft :: Windows
License-File: LICENSE.txt
Requires-Dist: pandas
Requires-Dist: nltk
Requires-Dist: torch
Requires-Dist: transformers
